{
  "youtube-vs-tiktok-analytics-creators": "lamrin",
  "youtube-trending-searches": "lamrin",
  "youtube-tracker": "zach-sanders",
  "youtube-shorts-title-best-practices-2026": "zach-sanders",
  "youtube-shorts-thumbnail-best-practices-2026": "elena",
  "youtube-shorts-posting-frequency-best-practices-2026": "lamrin",
  "youtube-shorts-length-best-practices": "lamrin",
  "youtube-shorts-ideas-without-showing-face": "maya",
  "youtube-shorts-hashtags-guide": "alex",
  "youtube-shorts-format": "lamrin",
  "youtube-shorts-content-ideas": "maya",
  "youtube-shorts-content-ideas-travel": "zach-sanders",
  "youtube-shorts-content-ideas-tech": "zach-sanders",
  "youtube-shorts-content-ideas-gaming": "alex",
  "youtube-shorts-content-ideas-fitness": "alex",
  "youtube-shorts-content-ideas-cooking": "zach-sanders",
  "youtube-shorts-content-ideas-beauty": "zach-sanders",
  "youtube-shorts-best-practices": "zach-sanders",
  "youtube-shorts-best-practices-evergreen": "elena",
  "youtube-shorts-analytics": "alex",
  "youtube-shorts-algorithm-2026": "elena",
  "what-makes-a-video-viral": "alex",
  "what-is-content-intelligence": "maya",
  "what-is-a-youtube-short": "elena",
  "what-is-a-reel": "alex",
  "viral-youtube-shorts-ideas-2026": "elena",
  "viral-youtube-shorts-hooks": "zach-sanders",
  "viral-tiktok-ideas-fashion": "maya",
  "vidiq-review": "zach-sanders",
  "vidiq-pricing": "elena",
  "vidiq-pricing-alternatives": "alex",
  "vidiq-alternatives": "lamrin",
  "vidiq-alternatives-gaming": "maya",
  "tubebuddy-vs-vidiq": "zach-sanders",
  "tubebuddy-review": "maya",
  "tubebuddy-free-alternatives": "zach-sanders",
  "tiktok-vs-youtube-shorts-analytics": "alex",
  "tiktok-vs-instagram-reels-creators": "zach-sanders",
  "tiktok-shop-marketing-strategy": "alex",
  "tiktok-hashtags-go-viral": "elena",
  "tiktok-content-strategy-business": "lamrin",
  "tiktok-competitor-analysis": "elena",
  "sprout-social-alternatives": "alex",
  "social-media-post-ideas": "lamrin",
  "social-media-marketing-ideas": "maya",
  "social-media-content-ideas": "lamrin",
  "social-media-analysis-guide": "lamrin",
  "post-ideas": "alex",
  "multi-platform-analytics-strategy": "maya",
  "metricool-pricing-alternatives": "elena",
  "marketing-competitor-analysis": "elena",
  "instagram-reels-vs-youtube-shorts-analytics": "lamrin",
  "instagram-reels-strategy-fitness": "elena",
  "instagram-reels-content-ideas": "alex",
  "instagram-reels-best-practices-2026": "maya",
  "instagram-reels-analytics": "elena",
  "instagram-competitor-analysis-tools": "elena",
  "instagram-analytics-app": "alex",
  "how-to-view-instagram-analytics": "alex",
  "how-to-upload-a-youtube-short": "elena",
  "how-to-track-youtube-shorts-competitors": "maya",
  "how-to-promote-youtube-shorts": "zach-sanders",
  "how-to-post-youtube-shorts": "maya",
  "how-to-monetize-youtube-shorts": "elena",
  "how-to-make-youtube-shorts": "alex",
  "how-to-make-a-youtube-short": "maya",
  "how-to-make-a-video-go-viral": "zach-sanders",
  "how-to-make-a-reel-on-instagram": "maya",
  "how-to-identify-market-trends": "lamrin",
  "how-to-grow-youtube-shorts-channel": "maya",
  "how-to-grow-gaming-youtube-shorts": "elena",
  "how-to-grow-fitness-youtube-shorts": "maya",
  "how-to-find-competitor-websites": "lamrin",
  "how-to-edit-youtube-shorts": "maya",
  "how-to-check-tiktok-analytics": "alex",
  "how-to-analyze-youtube-shorts-performance": "maya",
  "how-long-can-an-instagram-reel-be": "maya",
  "how-long-are-youtube-shorts": "lamrin",
  "hootsuite-alternatives-startups": "elena",
  "free-youtube-shorts-analytics": "alex",
  "find-winning-short-form-content": "alex",
  "educational-content-ideas-youtube-shorts": "zach-sanders",
  "creative-green-screen-ideas-youtube-shorts-2026": "elena",
  "conthunt-alternatives": "elena",
  "content-intelligence": "maya",
  "content-idea-generator": "zach-sanders",
  "content-generator": "alex",
  "content-creation-ideas": "lamrin",
  "competitor-analysis-tools": "alex",
  "competitive-content-analysis": "alex",
  "can-you-use-copyrighted-music-on-youtube-shorts": "elena",
  "buzzsumo-pricing-alternatives": "alex",
  "buzzsumo-alternatives-content-marketers": "lamrin",
  "best-time-to-post-youtube-shorts-2026": "alex",
  "best-social-media-monitoring-tools": "elena",
  "best-instagram-analytics-tools": "maya"
}